{"created_at":"Mon Sep 14 21:37:12 +0000 2015","id":643539015665364992,"id_str":"643539015665364992","text":"@brihonyspeed @SkyNewsAust   So why did #Julia get lambasted for saying a good government has lost its way?  #sexism","source":"\u003ca href=\"http:\/\/twitter.com\/#!\/download\/ipad\" rel=\"nofollow\"\u003eTwitter for iPad\u003c\/a\u003e","truncated":false,"in_reply_to_status_id":643538152058155008,"in_reply_to_status_id_str":"643538152058155008","in_reply_to_user_id":288708450,"in_reply_to_user_id_str":"288708450","in_reply_to_screen_name":"brihonyspeed","user":{"id":551483643,"id_str":"551483643","name":"Comrade Dame Judythe","screen_name":"muso1947","location":"Frightbat cave","url":null,"description":"Feminist, political tragic. Conservative loather. Abbott & his whole pathetic team must go!","protected":false,"verified":false,"followers_count":2054,"friends_count":2029,"listed_count":29,"favourites_count":45302,"statuses_count":43776,"created_at":"Wed Apr 11 23:26:29 +0000 2012","utc_offset":36000,"time_zone":"Brisbane","geo_enabled":false,"lang":"en","contributors_enabled":false,"is_translator":false,"profile_background_color":"C0DEED","profile_background_image_url":"http:\/\/abs.twimg.com\/images\/themes\/theme1\/bg.png","profile_background_image_url_https":"https:\/\/abs.twimg.com\/images\/themes\/theme1\/bg.png","profile_background_tile":false,"profile_link_color":"0084B4","profile_sidebar_border_color":"C0DEED","profile_sidebar_fill_color":"DDEEF6","profile_text_color":"333333","profile_use_background_image":true,"profile_image_url":"http:\/\/pbs.twimg.com\/profile_images\/588952249717497856\/ve6u9P5E_normal.jpg","profile_image_url_https":"https:\/\/pbs.twimg.com\/profile_images\/588952249717497856\/ve6u9P5E_normal.jpg","profile_banner_url":"https:\/\/pbs.twimg.com\/profile_banners\/551483643\/1429252489","default_profile":true,"default_profile_image":false,"following":null,"follow_request_sent":null,"notifications":null},"geo":null,"coordinates":null,"place":null,"contributors":null,"retweet_count":0,"favorite_count":0,"entities":{"hashtags":[{"text":"Julia","indices":[40,46]},{"text":"sexism","indices":[109,116]}],"trends":[],"urls":[],"user_mentions":[{"screen_name":"brihonyspeed","name":"Brihony Speed","id":288708450,"id_str":"288708450","indices":[0,13]},{"screen_name":"SkyNewsAust","name":"Sky News Australia","id":16834659,"id_str":"16834659","indices":[14,26]}],"symbols":[]},"favorited":false,"retweeted":false,"possibly_sensitive":true,"filter_level":"low","lang":"en","timestamp_ms":"1442266632368"}
