{"created_at":"Mon Sep 14 21:47:57 +0000 2015","id":643541720672661504,"id_str":"643541720672661504","text":"Without @TurnbullMalcolm going to an immediate election as @JuliaGillard did, this government will be ruling without our authority. ^PF","source":"\u003ca href=\"http:\/\/www.hootsuite.com\" rel=\"nofollow\"\u003eHootsuite\u003c\/a\u003e","truncated":false,"in_reply_to_status_id":null,"in_reply_to_status_id_str":null,"in_reply_to_user_id":null,"in_reply_to_user_id_str":null,"in_reply_to_screen_name":null,"user":{"id":108721985,"id_str":"108721985","name":"Peter Francis","screen_name":"peterfra","location":"Port Stephens NSW Australia","url":"http:\/\/paper.li\/peterfra\/1365735978","description":"Presenter, Speaker, Advocate, and Facilitator. Member @beyondblue Speakers Bureau","protected":false,"verified":false,"followers_count":1625,"friends_count":2001,"listed_count":111,"favourites_count":5594,"statuses_count":56999,"created_at":"Tue Jan 26 21:26:03 +0000 2010","utc_offset":36000,"time_zone":"Sydney","geo_enabled":false,"lang":"en","contributors_enabled":false,"is_translator":false,"profile_background_color":"0099B9","profile_background_image_url":"http:\/\/pbs.twimg.com\/profile_background_images\/378800000048397108\/5f50a5b0a9081976fa8b536906808a6a.jpeg","profile_background_image_url_https":"https:\/\/pbs.twimg.com\/profile_background_images\/378800000048397108\/5f50a5b0a9081976fa8b536906808a6a.jpeg","profile_background_tile":true,"profile_link_color":"0099B9","profile_sidebar_border_color":"FFFFFF","profile_sidebar_fill_color":"95E8EC","profile_text_color":"3C3940","profile_use_background_image":true,"profile_image_url":"http:\/\/pbs.twimg.com\/profile_images\/519980221911404544\/Dgj9Wvmg_normal.jpeg","profile_image_url_https":"https:\/\/pbs.twimg.com\/profile_images\/519980221911404544\/Dgj9Wvmg_normal.jpeg","profile_banner_url":"https:\/\/pbs.twimg.com\/profile_banners\/108721985\/1408668861","default_profile":false,"default_profile_image":false,"following":null,"follow_request_sent":null,"notifications":null},"geo":null,"coordinates":null,"place":null,"contributors":null,"retweet_count":0,"favorite_count":0,"entities":{"hashtags":[],"trends":[],"urls":[],"user_mentions":[{"screen_name":"TurnbullMalcolm","name":"Malcolm Turnbull","id":16734909,"id_str":"16734909","indices":[8,24]},{"screen_name":"JuliaGillard","name":"Julia Gillard","id":85436197,"id_str":"85436197","indices":[59,72]}],"symbols":[]},"favorited":false,"retweeted":false,"possibly_sensitive":false,"filter_level":"low","lang":"en","timestamp_ms":"1442267277292"}
