{"created_at":"Tue Sep 15 16:17:16 +0000 2015","id":643820889247744000,"id_str":"643820889247744000","text":"Scrum Master - TEKsystems - Alexandria, Virginia - TEKsystems has partnered up with a leading government integrato... http:\/\/t.co\/8bq0BC1e8p","source":"\u003ca href=\"http:\/\/www.hootsuite.com\" rel=\"nofollow\"\u003eHootsuite\u003c\/a\u003e","truncated":false,"in_reply_to_status_id":null,"in_reply_to_status_id_str":null,"in_reply_to_user_id":null,"in_reply_to_user_id_str":null,"in_reply_to_screen_name":null,"user":{"id":321382684,"id_str":"321382684","name":"TEKsystems IT Jobs","screen_name":"TEK_Reston","location":"Reston, VA","url":"http:\/\/www.teksystems.com\/locations\/teksystems-united-states\/reston","description":"Official Twitter account for the TEKsystems Reston office and for all jobs in and around Reston, Chantilly, Herndon and the surrounding areas.","protected":false,"verified":false,"followers_count":28,"friends_count":1,"listed_count":3,"favourites_count":0,"statuses_count":3179,"created_at":"Tue Jun 21 13:50:15 +0000 2011","utc_offset":null,"time_zone":null,"geo_enabled":false,"lang":"en","contributors_enabled":false,"is_translator":false,"profile_background_color":"021A32","profile_background_image_url":"http:\/\/pbs.twimg.com\/profile_background_images\/740902591\/fab9d91ecf2d62cfed4a8389c6c3e469.jpeg","profile_background_image_url_https":"https:\/\/pbs.twimg.com\/profile_background_images\/740902591\/fab9d91ecf2d62cfed4a8389c6c3e469.jpeg","profile_background_tile":false,"profile_link_color":"0094D3","profile_sidebar_border_color":"FFFFFF","profile_sidebar_fill_color":"F2F4F5","profile_text_color":"333333","profile_use_background_image":true,"profile_image_url":"http:\/\/pbs.twimg.com\/profile_images\/2987896137\/cc73132221741216b5b5b14cb69bb4e4_normal.jpeg","profile_image_url_https":"https:\/\/pbs.twimg.com\/profile_images\/2987896137\/cc73132221741216b5b5b14cb69bb4e4_normal.jpeg","default_profile":false,"default_profile_image":false,"following":null,"follow_request_sent":null,"notifications":null},"geo":null,"coordinates":null,"place":null,"contributors":null,"retweet_count":0,"favorite_count":0,"entities":{"hashtags":[],"trends":[],"urls":[{"url":"http:\/\/t.co\/8bq0BC1e8p","expanded_url":"http:\/\/ow.ly\/34aQ7E","display_url":"ow.ly\/34aQ7E","indices":[118,140]}],"user_mentions":[],"symbols":[]},"favorited":false,"retweeted":false,"possibly_sensitive":false,"filter_level":"low","lang":"en","timestamp_ms":"1442333836267"}
