{"created_at":"Thu Sep 17 17:53:39 +0000 2015","id":644569920982773760,"id_str":"644569920982773760","text":"No drones near pope http:\/\/t.co\/UWRfem4Rql  Special privilege maintained by irresponsible use of violence &amp; deceit is what government's for.","source":"\u003ca href=\"http:\/\/twitter.com\" rel=\"nofollow\"\u003eTwitter Web Client\u003c\/a\u003e","truncated":false,"in_reply_to_status_id":null,"in_reply_to_status_id_str":null,"in_reply_to_user_id":null,"in_reply_to_user_id_str":null,"in_reply_to_screen_name":null,"user":{"id":16659187,"id_str":"16659187","name":"@ChuckBaggett","screen_name":"ChuckBaggett","location":"Reporting, blocking, muting.","url":"http:\/\/twitter.com\/settings\/applications","description":"Please don't follow if you don't want to read my tweets. Peace & freedom are interests. Second Life engrossed me for yrs. Please unfollow instead of mute.","protected":false,"verified":false,"followers_count":4062,"friends_count":1801,"listed_count":310,"favourites_count":4680,"statuses_count":151771,"created_at":"Thu Oct 09 00:36:04 +0000 2008","utc_offset":-18000,"time_zone":"Central Time (US & Canada)","geo_enabled":true,"lang":"en","contributors_enabled":false,"is_translator":false,"profile_background_color":"0099B9","profile_background_image_url":"http:\/\/abs.twimg.com\/images\/themes\/theme4\/bg.gif","profile_background_image_url_https":"https:\/\/abs.twimg.com\/images\/themes\/theme4\/bg.gif","profile_background_tile":false,"profile_link_color":"0099B9","profile_sidebar_border_color":"000000","profile_sidebar_fill_color":"000000","profile_text_color":"000000","profile_use_background_image":true,"profile_image_url":"http:\/\/pbs.twimg.com\/profile_images\/569024716975767552\/7wDxDUiy_normal.png","profile_image_url_https":"https:\/\/pbs.twimg.com\/profile_images\/569024716975767552\/7wDxDUiy_normal.png","profile_banner_url":"https:\/\/pbs.twimg.com\/profile_banners\/16659187\/1440986090","default_profile":false,"default_profile_image":false,"following":null,"follow_request_sent":null,"notifications":null},"geo":null,"coordinates":null,"place":null,"contributors":null,"retweet_count":0,"favorite_count":0,"entities":{"hashtags":[],"trends":[],"urls":[{"url":"http:\/\/t.co\/UWRfem4Rql","expanded_url":"http:\/\/www.digitaltrends.com\/cool-tech\/no-drones-near-the-pope-please-says-the-faa\/","display_url":"digitaltrends.com\/cool-tech\/no-d\u2026","indices":[20,42]}],"user_mentions":[],"symbols":[]},"favorited":false,"retweeted":false,"possibly_sensitive":false,"filter_level":"low","lang":"en","timestamp_ms":"1442512419349"}
