{"created_at":"Mon Sep 14 21:42:45 +0000 2015","id":643540411705872385,"id_str":"643540411705872385","text":"RT @philippe_dam: Today is both #HRC30 1st day &amp; 2nd anniversary of #CaoShunli's arrest, blatant cases of reprisals: #China\nhttps:\/\/t.co\/aw\u2026","source":"\u003ca href=\"http:\/\/www.hootsuite.com\" rel=\"nofollow\"\u003eHootsuite\u003c\/a\u003e","truncated":false,"in_reply_to_status_id":null,"in_reply_to_status_id_str":null,"in_reply_to_user_id":null,"in_reply_to_user_id_str":null,"in_reply_to_screen_name":null,"user":{"id":294071256,"id_str":"294071256","name":"IFEX","screen_name":"IFEX","location":"","url":"http:\/\/www.ifex.org","description":"IFEX is the global human rights network of organisations defending the right to freedom of expression and information.","protected":false,"verified":false,"followers_count":9757,"friends_count":669,"listed_count":476,"favourites_count":340,"statuses_count":25517,"created_at":"Fri May 06 13:45:08 +0000 2011","utc_offset":-18000,"time_zone":"Quito","geo_enabled":false,"lang":"en","contributors_enabled":false,"is_translator":false,"profile_background_color":"ED1B24","profile_background_image_url":"http:\/\/pbs.twimg.com\/profile_background_images\/378800000114602958\/c6b44c15c452b548e120ca208daf9819.jpeg","profile_background_image_url_https":"https:\/\/pbs.twimg.com\/profile_background_images\/378800000114602958\/c6b44c15c452b548e120ca208daf9819.jpeg","profile_background_tile":true,"profile_link_color":"858585","profile_sidebar_border_color":"000000","profile_sidebar_fill_color":"FFFFFF","profile_text_color":"333333","profile_use_background_image":true,"profile_image_url":"http:\/\/pbs.twimg.com\/profile_images\/468795126672662528\/9BP_L0W5_normal.jpeg","profile_image_url_https":"https:\/\/pbs.twimg.com\/profile_images\/468795126672662528\/9BP_L0W5_normal.jpeg","profile_banner_url":"https:\/\/pbs.twimg.com\/profile_banners\/294071256\/1432756859","default_profile":false,"default_profile_image":false,"following":null,"follow_request_sent":null,"notifications":null},"geo":null,"coordinates":null,"place":null,"contributors":null,"retweeted_status":{"created_at":"Mon Sep 14 15:16:30 +0000 2015","id":643443210157752320,"id_str":"643443210157752320","text":"Today is both #HRC30 1st day &amp; 2nd anniversary of #CaoShunli's arrest, blatant cases of reprisals: #China\nhttps:\/\/t.co\/awv4c18Uwn\n@SophieHRW","source":"\u003ca href=\"http:\/\/twitter.com\" rel=\"nofollow\"\u003eTwitter Web Client\u003c\/a\u003e","truncated":false,"in_reply_to_status_id":null,"in_reply_to_status_id_str":null,"in_reply_to_user_id":null,"in_reply_to_user_id_str":null,"in_reply_to_screen_name":null,"user":{"id":49578312,"id_str":"49578312","name":"Philippe Dam","screen_name":"philippe_dam","location":"Human Rights Watch, Geneva","url":"http:\/\/www.hrw.org\/topic\/united-nations","description":"@HRW Advocate at the UN Human Rights Council (#HRC29 - #UPR22)\nViews expressed are my own.","protected":false,"verified":false,"followers_count":2402,"friends_count":832,"listed_count":87,"favourites_count":10,"statuses_count":1626,"created_at":"Mon Jun 22 08:56:24 +0000 2009","utc_offset":null,"time_zone":null,"geo_enabled":true,"lang":"en","contributors_enabled":false,"is_translator":false,"profile_background_color":"C0DEED","profile_background_image_url":"http:\/\/abs.twimg.com\/images\/themes\/theme1\/bg.png","profile_background_image_url_https":"https:\/\/abs.twimg.com\/images\/themes\/theme1\/bg.png","profile_background_tile":false,"profile_link_color":"0084B4","profile_sidebar_border_color":"C0DEED","profile_sidebar_fill_color":"DDEEF6","profile_text_color":"333333","profile_use_background_image":true,"profile_image_url":"http:\/\/pbs.twimg.com\/profile_images\/3560063678\/9855133ad5cf25c26cd0562cb12aed6c_normal.jpeg","profile_image_url_https":"https:\/\/pbs.twimg.com\/profile_images\/3560063678\/9855133ad5cf25c26cd0562cb12aed6c_normal.jpeg","default_profile":true,"default_profile_image":false,"following":null,"follow_request_sent":null,"notifications":null},"geo":null,"coordinates":null,"place":null,"contributors":null,"retweet_count":3,"favorite_count":3,"entities":{"hashtags":[{"text":"HRC30","indices":[14,20]},{"text":"CaoShunli","indices":[54,64]},{"text":"China","indices":[103,109]}],"trends":[],"urls":[{"url":"https:\/\/t.co\/awv4c18Uwn","expanded_url":"https:\/\/www.hrw.org\/news\/2015\/09\/14\/china-government-should-account-activists-detention-death","display_url":"hrw.org\/news\/2015\/09\/1\u2026","indices":[110,133]}],"user_mentions":[{"screen_name":"SophieHRW","name":"Sophie Richardson","id":55650719,"id_str":"55650719","indices":[134,144]}],"symbols":[]},"favorited":false,"retweeted":false,"possibly_sensitive":false,"filter_level":"low","lang":"en"},"retweet_count":0,"favorite_count":0,"entities":{"hashtags":[{"text":"HRC30","indices":[32,38]},{"text":"CaoShunli","indices":[72,82]},{"text":"China","indices":[121,127]}],"trends":[],"urls":[{"url":"https:\/\/t.co\/awv4c18Uwn","expanded_url":"https:\/\/www.hrw.org\/news\/2015\/09\/14\/china-government-should-account-activists-detention-death","display_url":"hrw.org\/news\/2015\/09\/1\u2026","indices":[128,144]}],"user_mentions":[{"screen_name":"philippe_dam","name":"Philippe Dam","id":49578312,"id_str":"49578312","indices":[3,16]},{"screen_name":"SophieHRW","name":"Sophie Richardson","id":55650719,"id_str":"55650719","indices":[143,144]}],"symbols":[]},"favorited":false,"retweeted":false,"possibly_sensitive":false,"filter_level":"low","lang":"en","timestamp_ms":"1442266965210"}
