{"created_at":"Thu Sep 10 20:30:03 +0000 2015","id":642072565352132609,"id_str":"642072565352132609","text":"I really wish people knew the difference between a council and a government decision.","source":"\u003ca href=\"http:\/\/twitter.com\/download\/android\" rel=\"nofollow\"\u003eTwitter for Android\u003c\/a\u003e","truncated":false,"in_reply_to_status_id":null,"in_reply_to_status_id_str":null,"in_reply_to_user_id":null,"in_reply_to_user_id_str":null,"in_reply_to_screen_name":null,"user":{"id":548828443,"id_str":"548828443","name":"Ryan \u2708","screen_name":"Ryan_B767","location":"Sheffield \/ MediaCity UK","url":null,"description":"18 years young! Aviation Enthusiast! Background Web Developer, weird, arrogant + opinionated. Yeah thats practically it oh and I love @0mfgdanixo","protected":false,"verified":false,"followers_count":1658,"friends_count":1945,"listed_count":1,"favourites_count":628,"statuses_count":324,"created_at":"Mon Apr 09 00:46:27 +0000 2012","utc_offset":3600,"time_zone":"London","geo_enabled":true,"lang":"en","contributors_enabled":false,"is_translator":false,"profile_background_color":"131516","profile_background_image_url":"http:\/\/abs.twimg.com\/images\/themes\/theme14\/bg.gif","profile_background_image_url_https":"https:\/\/abs.twimg.com\/images\/themes\/theme14\/bg.gif","profile_background_tile":true,"profile_link_color":"B6C208","profile_sidebar_border_color":"EEEEEE","profile_sidebar_fill_color":"EFEFEF","profile_text_color":"333333","profile_use_background_image":true,"profile_image_url":"http:\/\/pbs.twimg.com\/profile_images\/633081209883635712\/saWh9PF__normal.jpg","profile_image_url_https":"https:\/\/pbs.twimg.com\/profile_images\/633081209883635712\/saWh9PF__normal.jpg","profile_banner_url":"https:\/\/pbs.twimg.com\/profile_banners\/548828443\/1439483905","default_profile":false,"default_profile_image":false,"following":null,"follow_request_sent":null,"notifications":null},"geo":null,"coordinates":null,"place":null,"contributors":null,"retweet_count":0,"favorite_count":0,"entities":{"hashtags":[],"trends":[],"urls":[],"user_mentions":[],"symbols":[]},"favorited":false,"retweeted":false,"possibly_sensitive":false,"filter_level":"low","lang":"en","timestamp_ms":"1441917003368"}
