{"created_at":"Thu Sep 10 20:26:54 +0000 2015","id":642071772410605568,"id_str":"642071772410605568","text":"#Refugees r not the problem!Those who created #ClimateChange r!\nhttp:\/\/t.co\/UlTWTfwITx #RefugeesWelcome #uniteblue 10,000 Syrian #UniteBlue","source":"\u003ca href=\"http:\/\/twitter.com\" rel=\"nofollow\"\u003eTwitter Web Client\u003c\/a\u003e","truncated":false,"in_reply_to_status_id":null,"in_reply_to_status_id_str":null,"in_reply_to_user_id":null,"in_reply_to_user_id_str":null,"in_reply_to_screen_name":null,"user":{"id":392371508,"id_str":"392371508","name":"Isabell Tolling :D","screen_name":"IsabellTolling","location":"Planet Earth ","url":null,"description":"Photographer @RGIventures | Founder @EdiblEden @HealthyIn10Min @CookingAboard @MooreIdeasOrg @WhatDoPplWant | Lover of Science #CleanAir #UniteBlue #Progressive","protected":false,"verified":false,"followers_count":914,"friends_count":1990,"listed_count":35,"favourites_count":5560,"statuses_count":3026,"created_at":"Sun Oct 16 22:58:28 +0000 2011","utc_offset":-10800,"time_zone":"Atlantic Time (Canada)","geo_enabled":false,"lang":"en","contributors_enabled":false,"is_translator":false,"profile_background_color":"BADFCD","profile_background_image_url":"http:\/\/abs.twimg.com\/images\/themes\/theme12\/bg.gif","profile_background_image_url_https":"https:\/\/abs.twimg.com\/images\/themes\/theme12\/bg.gif","profile_background_tile":false,"profile_link_color":"FF0000","profile_sidebar_border_color":"FFFFFF","profile_sidebar_fill_color":"FFF7CC","profile_text_color":"0C3E53","profile_use_background_image":true,"profile_image_url":"http:\/\/pbs.twimg.com\/profile_images\/642026811241533440\/VO1NpXXV_normal.jpg","profile_image_url_https":"https:\/\/pbs.twimg.com\/profile_images\/642026811241533440\/VO1NpXXV_normal.jpg","profile_banner_url":"https:\/\/pbs.twimg.com\/profile_banners\/392371508\/1371319005","default_profile":false,"default_profile_image":false,"following":null,"follow_request_sent":null,"notifications":null},"geo":null,"coordinates":null,"place":null,"contributors":null,"retweet_count":0,"favorite_count":0,"entities":{"hashtags":[{"text":"Refugees","indices":[0,9]},{"text":"ClimateChange","indices":[46,60]},{"text":"RefugeesWelcome","indices":[87,103]},{"text":"uniteblue","indices":[104,114]},{"text":"UniteBlue","indices":[129,139]}],"trends":[],"urls":[{"url":"http:\/\/t.co\/UlTWTfwITx","expanded_url":"http:\/\/time.com\/4024210\/climate-change-migrants\/","display_url":"time.com\/4024210\/climat\u2026","indices":[64,86]}],"user_mentions":[],"symbols":[]},"favorited":false,"retweeted":false,"possibly_sensitive":false,"filter_level":"low","lang":"en","timestamp_ms":"1441916814316"}
