{"created_at":"Thu Sep 10 20:27:29 +0000 2015","id":642071921237094400,"id_str":"642071921237094400","text":"RT @PremiumTimesng: Our New Nigeria: The Role of Professionals In Government, By Kayode\u00a0Fayemi http:\/\/t.co\/maN34MyK0k","source":"\u003ca href=\"http:\/\/twitter.com\/download\/android\" rel=\"nofollow\"\u003eTwitter for Android\u003c\/a\u003e","truncated":false,"in_reply_to_status_id":null,"in_reply_to_status_id_str":null,"in_reply_to_user_id":null,"in_reply_to_user_id_str":null,"in_reply_to_screen_name":null,"user":{"id":17130422,"id_str":"17130422","name":"Gbenga Olorunpomi","screen_name":"GbengaGOLD","location":"Lagos, Nigeria","url":"https:\/\/ng.linkedin.com\/in\/gbengaolorunpomi","description":"Nigeriaist. Digital Marketing Expert. Husband. Dad. RT \u2260 Endorsement.","protected":false,"verified":false,"followers_count":16713,"friends_count":2756,"listed_count":67,"favourites_count":4589,"statuses_count":110383,"created_at":"Mon Nov 03 13:36:32 +0000 2008","utc_offset":3600,"time_zone":"West Central Africa","geo_enabled":true,"lang":"en","contributors_enabled":false,"is_translator":false,"profile_background_color":"EDECE9","profile_background_image_url":"http:\/\/pbs.twimg.com\/profile_background_images\/551842995901698048\/lcNuhkUd.jpeg","profile_background_image_url_https":"https:\/\/pbs.twimg.com\/profile_background_images\/551842995901698048\/lcNuhkUd.jpeg","profile_background_tile":true,"profile_link_color":"9266CC","profile_sidebar_border_color":"FFFFFF","profile_sidebar_fill_color":"E3E2DE","profile_text_color":"634047","profile_use_background_image":true,"profile_image_url":"http:\/\/pbs.twimg.com\/profile_images\/630597236326592512\/HjXjJbGu_normal.jpg","profile_image_url_https":"https:\/\/pbs.twimg.com\/profile_images\/630597236326592512\/HjXjJbGu_normal.jpg","profile_banner_url":"https:\/\/pbs.twimg.com\/profile_banners\/17130422\/1441349348","default_profile":false,"default_profile_image":false,"following":null,"follow_request_sent":null,"notifications":null},"geo":null,"coordinates":null,"place":null,"contributors":null,"retweeted_status":{"created_at":"Thu Sep 10 19:04:02 +0000 2015","id":642050920939806720,"id_str":"642050920939806720","text":"Our New Nigeria: The Role of Professionals In Government, By Kayode\u00a0Fayemi http:\/\/t.co\/maN34MyK0k","source":"\u003ca href=\"http:\/\/publicize.wp.com\/\" rel=\"nofollow\"\u003eWordPress.com\u003c\/a\u003e","truncated":false,"in_reply_to_status_id":null,"in_reply_to_status_id_str":null,"in_reply_to_user_id":null,"in_reply_to_user_id_str":null,"in_reply_to_screen_name":null,"user":{"id":373978904,"id_str":"373978904","name":"Premium Times","screen_name":"PremiumTimesng","location":"Abuja, Nigeria","url":"http:\/\/www.premiumtimesng.com","description":"A multimedia Nigerian publication based in Abuja delivering fresh, factual & reliable news","protected":false,"verified":false,"followers_count":280704,"friends_count":249,"listed_count":499,"favourites_count":68,"statuses_count":104417,"created_at":"Thu Sep 15 14:08:13 +0000 2011","utc_offset":3600,"time_zone":"West Central Africa","geo_enabled":true,"lang":"en","contributors_enabled":false,"is_translator":false,"profile_background_color":"616161","profile_background_image_url":"http:\/\/pbs.twimg.com\/profile_background_images\/725660384\/a280e00c2ab598b55fd9c70d045ea3d2.jpeg","profile_background_image_url_https":"https:\/\/pbs.twimg.com\/profile_background_images\/725660384\/a280e00c2ab598b55fd9c70d045ea3d2.jpeg","profile_background_tile":false,"profile_link_color":"AD0002","profile_sidebar_border_color":"FFFFFF","profile_sidebar_fill_color":"D6D6D6","profile_text_color":"333333","profile_use_background_image":true,"profile_image_url":"http:\/\/pbs.twimg.com\/profile_images\/475921164007522305\/IavOdy1O_normal.jpeg","profile_image_url_https":"https:\/\/pbs.twimg.com\/profile_images\/475921164007522305\/IavOdy1O_normal.jpeg","profile_banner_url":"https:\/\/pbs.twimg.com\/profile_banners\/373978904\/1398963112","default_profile":false,"default_profile_image":false,"following":null,"follow_request_sent":null,"notifications":null},"geo":null,"coordinates":null,"place":null,"contributors":null,"retweet_count":12,"favorite_count":7,"entities":{"hashtags":[],"trends":[],"urls":[{"url":"http:\/\/t.co\/maN34MyK0k","expanded_url":"http:\/\/blogs.premiumtimesng.com\/?p=168831","display_url":"blogs.premiumtimesng.com\/?p=168831","indices":[75,97]}],"user_mentions":[],"symbols":[]},"favorited":false,"retweeted":false,"possibly_sensitive":false,"filter_level":"low","lang":"en"},"retweet_count":0,"favorite_count":0,"entities":{"hashtags":[],"trends":[],"urls":[{"url":"http:\/\/t.co\/maN34MyK0k","expanded_url":"http:\/\/blogs.premiumtimesng.com\/?p=168831","display_url":"blogs.premiumtimesng.com\/?p=168831","indices":[95,117]}],"user_mentions":[{"screen_name":"PremiumTimesng","name":"Premium Times","id":373978904,"id_str":"373978904","indices":[3,18]}],"symbols":[]},"favorited":false,"retweeted":false,"possibly_sensitive":false,"filter_level":"low","lang":"en","timestamp_ms":"1441916849799"}
