{"created_at":"Thu Sep 17 17:54:04 +0000 2015","id":644570027857842176,"id_str":"644570027857842176","text":"DR Congo politicians expelled from government: Politicians who voiced concerns about possible third presidenti... http:\/\/t.co\/pBK0ovdMrm","source":"\u003ca href=\"http:\/\/twitterfeed.com\" rel=\"nofollow\"\u003etwitterfeed\u003c\/a\u003e","truncated":false,"in_reply_to_status_id":null,"in_reply_to_status_id_str":null,"in_reply_to_user_id":null,"in_reply_to_user_id_str":null,"in_reply_to_screen_name":null,"user":{"id":16791363,"id_str":"16791363","name":"MWC","screen_name":"mwcnews","location":"Canada","url":"http:\/\/mwcnews.net\/","description":"MWC News- Alternative news, uncompromising, unapologetic, uncensored.","protected":false,"verified":false,"followers_count":579,"friends_count":644,"listed_count":57,"favourites_count":626,"statuses_count":68374,"created_at":"Wed Oct 15 19:57:00 +0000 2008","utc_offset":-25200,"time_zone":"Pacific Time (US & Canada)","geo_enabled":false,"lang":"en","contributors_enabled":false,"is_translator":false,"profile_background_color":"FFFFFF","profile_background_image_url":"http:\/\/pbs.twimg.com\/profile_background_images\/486576087\/Untitled-2.jpg","profile_background_image_url_https":"https:\/\/pbs.twimg.com\/profile_background_images\/486576087\/Untitled-2.jpg","profile_background_tile":true,"profile_link_color":"2891E2","profile_sidebar_border_color":"FFFFFF","profile_sidebar_fill_color":"BABAB2","profile_text_color":"47484D","profile_use_background_image":true,"profile_image_url":"http:\/\/pbs.twimg.com\/profile_images\/567499566983815168\/-qalMxCT_normal.jpeg","profile_image_url_https":"https:\/\/pbs.twimg.com\/profile_images\/567499566983815168\/-qalMxCT_normal.jpeg","profile_banner_url":"https:\/\/pbs.twimg.com\/profile_banners\/16791363\/1398210228","default_profile":false,"default_profile_image":false,"following":null,"follow_request_sent":null,"notifications":null},"geo":null,"coordinates":null,"place":null,"contributors":null,"retweet_count":0,"favorite_count":0,"entities":{"hashtags":[],"trends":[],"urls":[{"url":"http:\/\/t.co\/pBK0ovdMrm","expanded_url":"http:\/\/bit.ly\/1OzJPTO","display_url":"bit.ly\/1OzJPTO","indices":[114,136]}],"user_mentions":[],"symbols":[]},"favorited":false,"retweeted":false,"possibly_sensitive":false,"filter_level":"low","lang":"en","timestamp_ms":"1442512444830"}
