{"created_at":"Mon Sep 14 21:29:12 +0000 2015","id":643537004559470592,"id_str":"643537004559470592","text":"@WHAAsstSecty @USUN Madame Secretary United States Government should be openly outraged at flagrant abuse of defenseless women in #Cuba.","source":"\u003ca href=\"http:\/\/twitter.com\/download\/iphone\" rel=\"nofollow\"\u003eTwitter for iPhone\u003c\/a\u003e","truncated":false,"in_reply_to_status_id":643441428006334464,"in_reply_to_status_id_str":"643441428006334464","in_reply_to_user_id":97190495,"in_reply_to_user_id_str":"97190495","in_reply_to_screen_name":"WHAAsstSecty","user":{"id":3393186119,"id_str":"3393186119","name":"Fernando Amandi Sr.","screen_name":"FernandoAmandi","location":"","url":null,"description":"Advocate for Freedom, Human Rights, Peace through Strength, Social Justice, Law and Order, Education and Animal Rights.","protected":false,"verified":false,"followers_count":66,"friends_count":140,"listed_count":0,"favourites_count":369,"statuses_count":680,"created_at":"Wed Jul 29 03:55:54 +0000 2015","utc_offset":null,"time_zone":null,"geo_enabled":false,"lang":"en","contributors_enabled":false,"is_translator":false,"profile_background_color":"C0DEED","profile_background_image_url":"http:\/\/abs.twimg.com\/images\/themes\/theme1\/bg.png","profile_background_image_url_https":"https:\/\/abs.twimg.com\/images\/themes\/theme1\/bg.png","profile_background_tile":false,"profile_link_color":"0084B4","profile_sidebar_border_color":"C0DEED","profile_sidebar_fill_color":"DDEEF6","profile_text_color":"333333","profile_use_background_image":true,"profile_image_url":"http:\/\/pbs.twimg.com\/profile_images\/633759609174519808\/WfWDHfXo_normal.jpg","profile_image_url_https":"https:\/\/pbs.twimg.com\/profile_images\/633759609174519808\/WfWDHfXo_normal.jpg","default_profile":true,"default_profile_image":false,"following":null,"follow_request_sent":null,"notifications":null},"geo":null,"coordinates":null,"place":null,"contributors":null,"retweet_count":0,"favorite_count":0,"entities":{"hashtags":[{"text":"Cuba","indices":[130,135]}],"trends":[],"urls":[],"user_mentions":[{"screen_name":"WHAAsstSecty","name":"Roberta Jacobson","id":97190495,"id_str":"97190495","indices":[0,13]},{"screen_name":"USUN","name":"US Mission to the UN","id":249677516,"id_str":"249677516","indices":[14,19]}],"symbols":[]},"favorited":false,"retweeted":false,"possibly_sensitive":false,"filter_level":"low","lang":"en","timestamp_ms":"1442266152883"}
