{"created_at":"Tue Sep 15 16:09:53 +0000 2015","id":643819033935024128,"id_str":"643819033935024128","text":"@Vickie627 \"39 percent said PP should not receive government funding and 34 percent said federal dollars should continue\" Your Reuters link.","source":"\u003ca href=\"http:\/\/twitter.com\" rel=\"nofollow\"\u003eTwitter Web Client\u003c\/a\u003e","truncated":false,"in_reply_to_status_id":643816684361396224,"in_reply_to_status_id_str":"643816684361396224","in_reply_to_user_id":189042188,"in_reply_to_user_id_str":"189042188","in_reply_to_screen_name":"Vickie627","user":{"id":416696463,"id_str":"416696463","name":"Gunny Dave USMC","screen_name":"dave_usmc","location":"#2A Defender","url":null,"description":"U.S. Marine, leftists hate me, and I swear a lot. Hockey fan. Just #AnotherBoy. Read and heed the pinned tweet. Good to go?","protected":false,"verified":false,"followers_count":15520,"friends_count":14316,"listed_count":288,"favourites_count":12831,"statuses_count":41430,"created_at":"Sun Nov 20 01:17:24 +0000 2011","utc_offset":-25200,"time_zone":"Arizona","geo_enabled":false,"lang":"en","contributors_enabled":false,"is_translator":false,"profile_background_color":"654321","profile_background_image_url":"http:\/\/pbs.twimg.com\/profile_background_images\/572088975402086400\/r3WosBtn.jpeg","profile_background_image_url_https":"https:\/\/pbs.twimg.com\/profile_background_images\/572088975402086400\/r3WosBtn.jpeg","profile_background_tile":true,"profile_link_color":"C2B280","profile_sidebar_border_color":"FFFFFF","profile_sidebar_fill_color":"DDEEF6","profile_text_color":"333333","profile_use_background_image":true,"profile_image_url":"http:\/\/pbs.twimg.com\/profile_images\/543850204542152704\/-Qk0wNP2_normal.png","profile_image_url_https":"https:\/\/pbs.twimg.com\/profile_images\/543850204542152704\/-Qk0wNP2_normal.png","profile_banner_url":"https:\/\/pbs.twimg.com\/profile_banners\/416696463\/1405625929","default_profile":false,"default_profile_image":false,"following":null,"follow_request_sent":null,"notifications":null},"geo":null,"coordinates":null,"place":null,"contributors":null,"retweet_count":0,"favorite_count":0,"entities":{"hashtags":[],"trends":[],"urls":[],"user_mentions":[{"screen_name":"Vickie627","name":"V\u2764\ufe0f","id":189042188,"id_str":"189042188","indices":[0,10]}],"symbols":[]},"favorited":false,"retweeted":false,"possibly_sensitive":false,"filter_level":"low","lang":"en","timestamp_ms":"1442333393926"}
