{"created_at":"Mon Sep 14 21:26:14 +0000 2015","id":643536256979353601,"id_str":"643536256979353601","text":"Politics and Religion Should NOT Mix\n\nhttp:\/\/t.co\/F6AXCQFB53","source":"\u003ca href=\"http:\/\/twitter.com\/download\/android\" rel=\"nofollow\"\u003eTwitter for Android\u003c\/a\u003e","truncated":false,"in_reply_to_status_id":null,"in_reply_to_status_id_str":null,"in_reply_to_user_id":null,"in_reply_to_user_id_str":null,"in_reply_to_screen_name":null,"user":{"id":1014439928,"id_str":"1014439928","name":" Irma ","screen_name":"Irmitariii","location":"","url":null,"description":"\u043c\u03b1\u2202\u0454 \u03b9\u03b7 \u03c1\u03c5\u0454\u044f\u0442\u03c3 \u044f\u03b9\u00a2\u03c3 \r\n\u2113\u03b9\u03bd\u0454 \u03b9\u03b7 \u00a2\u043d\u03b9\u00a2\u03b1g\u03c3 ...  \u044f\u03b1\u03b7\u2202\u03c3\u043c \u0442\u03c9\u0454\u0454\u0442\u0455, \u03c9\u043d\u03b1\u0442\u0454\u03bd\u0454\u044f \u0192\u2113\u03c3\u03b1\u0442\u0455 \u03b9\u03b7 \u043c\u0443 \u043d\u0454\u03b1\u2202 \u03b1\u03b7\u2202 \u043d\u0454\u03b1\u044f\u0442.","protected":false,"verified":false,"followers_count":1327,"friends_count":1105,"listed_count":16,"favourites_count":1658,"statuses_count":29720,"created_at":"Sun Dec 16 03:57:36 +0000 2012","utc_offset":-18000,"time_zone":"Central Time (US & Canada)","geo_enabled":true,"lang":"en","contributors_enabled":false,"is_translator":false,"profile_background_color":"DD2E44","profile_background_image_url":"http:\/\/pbs.twimg.com\/profile_background_images\/639773627227836416\/d8aJvsY_.jpg","profile_background_image_url_https":"https:\/\/pbs.twimg.com\/profile_background_images\/639773627227836416\/d8aJvsY_.jpg","profile_background_tile":true,"profile_link_color":"DD2E44","profile_sidebar_border_color":"FFFFFF","profile_sidebar_fill_color":"77707E","profile_text_color":"C705FF","profile_use_background_image":true,"profile_image_url":"http:\/\/pbs.twimg.com\/profile_images\/603900743825817600\/gfrpdX53_normal.jpg","profile_image_url_https":"https:\/\/pbs.twimg.com\/profile_images\/603900743825817600\/gfrpdX53_normal.jpg","profile_banner_url":"https:\/\/pbs.twimg.com\/profile_banners\/1014439928\/1428974094","default_profile":false,"default_profile_image":false,"following":null,"follow_request_sent":null,"notifications":null},"geo":null,"coordinates":null,"place":null,"contributors":null,"retweet_count":0,"favorite_count":0,"entities":{"hashtags":[],"trends":[],"urls":[{"url":"http:\/\/t.co\/F6AXCQFB53","expanded_url":"http:\/\/flip.it\/LQomg","display_url":"flip.it\/LQomg","indices":[38,60]}],"user_mentions":[],"symbols":[]},"favorited":false,"retweeted":false,"possibly_sensitive":false,"filter_level":"low","lang":"en","timestamp_ms":"1442265974646"}
