{"created_at":"Mon Sep 14 21:39:03 +0000 2015","id":643539482961137665,"id_str":"643539482961137665","text":"@LucieEWiltshire Goooo Lucieeeee! Shame we don't have art lessons to talk politics in anymore\ud83d\udc94","source":"\u003ca href=\"http:\/\/twitter.com\/download\/iphone\" rel=\"nofollow\"\u003eTwitter for iPhone\u003c\/a\u003e","truncated":false,"in_reply_to_status_id":642968195444396032,"in_reply_to_status_id_str":"642968195444396032","in_reply_to_user_id":1923835022,"in_reply_to_user_id_str":"1923835022","in_reply_to_screen_name":"LucieEWiltshire","user":{"id":39291316,"id_str":"39291316","name":"Alice Olivia","screen_name":"AliceOliviaLee_","location":"South Wales, United Kingdom ","url":null,"description":"BE THE CHANGE","protected":false,"verified":false,"followers_count":846,"friends_count":695,"listed_count":2,"favourites_count":12356,"statuses_count":11490,"created_at":"Mon May 11 17:06:43 +0000 2009","utc_offset":3600,"time_zone":"London","geo_enabled":true,"lang":"en","contributors_enabled":false,"is_translator":false,"profile_background_color":"74B893","profile_background_image_url":"http:\/\/pbs.twimg.com\/profile_background_images\/746448488\/6df90967cca58a36588d34e8f1753558.jpeg","profile_background_image_url_https":"https:\/\/pbs.twimg.com\/profile_background_images\/746448488\/6df90967cca58a36588d34e8f1753558.jpeg","profile_background_tile":true,"profile_link_color":"F4775B","profile_sidebar_border_color":"FFFFFF","profile_sidebar_fill_color":"E2336E","profile_text_color":"9BF3CE","profile_use_background_image":true,"profile_image_url":"http:\/\/pbs.twimg.com\/profile_images\/633236640450805761\/7GtvQR7B_normal.png","profile_image_url_https":"https:\/\/pbs.twimg.com\/profile_images\/633236640450805761\/7GtvQR7B_normal.png","profile_banner_url":"https:\/\/pbs.twimg.com\/profile_banners\/39291316\/1437772588","default_profile":false,"default_profile_image":false,"following":null,"follow_request_sent":null,"notifications":null},"geo":null,"coordinates":null,"place":null,"contributors":null,"retweet_count":0,"favorite_count":0,"entities":{"hashtags":[],"trends":[],"urls":[],"user_mentions":[{"screen_name":"LucieEWiltshire","name":"Lucie","id":1923835022,"id_str":"1923835022","indices":[0,16]}],"symbols":[]},"favorited":false,"retweeted":false,"possibly_sensitive":false,"filter_level":"low","lang":"en","timestamp_ms":"1442266743780"}
