{"created_at":"Wed Sep 16 20:16:50 +0000 2015","id":644243568941359105,"id_str":"644243568941359105","text":"Strine Senator Macdonald demands Aussie senators stop speaking English. #auspol http:\/\/t.co\/jaiHugbNZ3","source":"\u003ca href=\"http:\/\/twitter.com\/#!\/download\/ipad\" rel=\"nofollow\"\u003eTwitter for iPad\u003c\/a\u003e","truncated":false,"in_reply_to_status_id":null,"in_reply_to_status_id_str":null,"in_reply_to_user_id":null,"in_reply_to_user_id_str":null,"in_reply_to_screen_name":null,"user":{"id":278897147,"id_str":"278897147","name":"Sir Kevin","screen_name":"kbkorb","location":"Melbourne, Australia","url":"http:\/\/www.csse.monash.edu.au\/~korb","description":"Knight of the Order of Abbott and Costello and occasional researcher of causal Bayesian networks, Bayesian philosophy of science, evolutionary ALife and logic.","protected":false,"verified":false,"followers_count":284,"friends_count":657,"listed_count":16,"favourites_count":41,"statuses_count":6455,"created_at":"Fri Apr 08 05:34:46 +0000 2011","utc_offset":36000,"time_zone":"Melbourne","geo_enabled":false,"lang":"en","contributors_enabled":false,"is_translator":false,"profile_background_color":"C0DEED","profile_background_image_url":"http:\/\/abs.twimg.com\/images\/themes\/theme1\/bg.png","profile_background_image_url_https":"https:\/\/abs.twimg.com\/images\/themes\/theme1\/bg.png","profile_background_tile":false,"profile_link_color":"0084B4","profile_sidebar_border_color":"C0DEED","profile_sidebar_fill_color":"DDEEF6","profile_text_color":"333333","profile_use_background_image":true,"profile_image_url":"http:\/\/pbs.twimg.com\/profile_images\/485355195145007104\/sZTUNIyI_normal.jpeg","profile_image_url_https":"https:\/\/pbs.twimg.com\/profile_images\/485355195145007104\/sZTUNIyI_normal.jpeg","default_profile":true,"default_profile_image":false,"following":null,"follow_request_sent":null,"notifications":null},"geo":null,"coordinates":null,"place":null,"contributors":null,"retweet_count":0,"favorite_count":0,"entities":{"hashtags":[{"text":"auspol","indices":[72,79]}],"trends":[],"urls":[{"url":"http:\/\/t.co\/jaiHugbNZ3","expanded_url":"http:\/\/www.skynews.com.au\/news\/politics\/national\/2015\/09\/16\/labor-senator-told-to--speak-australian-.html","display_url":"skynews.com.au\/news\/politics\/\u2026","indices":[80,102]}],"user_mentions":[],"symbols":[]},"favorited":false,"retweeted":false,"possibly_sensitive":false,"filter_level":"low","lang":"en","timestamp_ms":"1442434610959"}
