{"created_at":"Mon Sep 14 21:32:09 +0000 2015","id":643537743767859205,"id_str":"643537743767859205","text":"@emsiekatexo that's how elections work though","source":"\u003ca href=\"http:\/\/twitter.com\/download\/iphone\" rel=\"nofollow\"\u003eTwitter for iPhone\u003c\/a\u003e","truncated":false,"in_reply_to_status_id":643509558762172417,"in_reply_to_status_id_str":"643509558762172417","in_reply_to_user_id":151106273,"in_reply_to_user_id_str":"151106273","in_reply_to_screen_name":"emsiekatexo","user":{"id":19553322,"id_str":"19553322","name":"Harry Matthews","screen_name":"hmatthews92","location":"Silchester","url":"http:\/\/atrebatum.org.uk","description":"i do things (mainly cats and politics)","protected":false,"verified":false,"followers_count":1827,"friends_count":1288,"listed_count":88,"favourites_count":2510,"statuses_count":84831,"created_at":"Mon Jan 26 19:57:29 +0000 2009","utc_offset":3600,"time_zone":"London","geo_enabled":true,"lang":"en","contributors_enabled":false,"is_translator":false,"profile_background_color":"022330","profile_background_image_url":"http:\/\/abs.twimg.com\/images\/themes\/theme15\/bg.png","profile_background_image_url_https":"https:\/\/abs.twimg.com\/images\/themes\/theme15\/bg.png","profile_background_tile":false,"profile_link_color":"FDBC30","profile_sidebar_border_color":"A8C7F7","profile_sidebar_fill_color":"C0DFEC","profile_text_color":"333333","profile_use_background_image":true,"profile_image_url":"http:\/\/pbs.twimg.com\/profile_images\/637677300704780288\/xYIWxK2p_normal.png","profile_image_url_https":"https:\/\/pbs.twimg.com\/profile_images\/637677300704780288\/xYIWxK2p_normal.png","profile_banner_url":"https:\/\/pbs.twimg.com\/profile_banners\/19553322\/1436130372","default_profile":false,"default_profile_image":false,"following":null,"follow_request_sent":null,"notifications":null},"geo":null,"coordinates":null,"place":{"id":"06168d1feda43857","url":"https:\/\/api.twitter.com\/1.1\/geo\/id\/06168d1feda43857.json","place_type":"admin","name":"South East","full_name":"South East, England","country_code":"GB","country":"United Kingdom","bounding_box":{"type":"Polygon","coordinates":[[[-1.95729593780907,50.5746064789388],[-1.95729593780907,52.1962850088601],[1.45178800018019,52.1962850088601],[1.45178800018019,50.5746064789388]]]},"attributes":{}},"contributors":null,"retweet_count":0,"favorite_count":0,"entities":{"hashtags":[],"trends":[],"urls":[],"user_mentions":[{"screen_name":"emsiekatexo","name":"Ems Simpson","id":151106273,"id_str":"151106273","indices":[0,12]}],"symbols":[]},"favorited":false,"retweeted":false,"possibly_sensitive":false,"filter_level":"low","lang":"en","timestamp_ms":"1442266329124"}
