{"created_at":"Sat Sep 12 19:54:49 +0000 2015","id":642788473771044864,"id_str":"642788473771044864","text":"And I know the government administer AIDS, so I guess we just pray like the minister say","source":"\u003ca href=\"http:\/\/twitter.com\/download\/android\" rel=\"nofollow\"\u003eTwitter for Android\u003c\/a\u003e","truncated":false,"in_reply_to_status_id":null,"in_reply_to_status_id_str":null,"in_reply_to_user_id":null,"in_reply_to_user_id_str":null,"in_reply_to_screen_name":null,"user":{"id":105344421,"id_str":"105344421","name":"Cassius Clay","screen_name":"TrackIsMyCrack","location":"Road to Rio","url":null,"description":"I run because im blessed. I'm blessed because i run. My goal is simple, shock the world #KnicksNation #ColtsNation","protected":false,"verified":false,"followers_count":1897,"friends_count":2101,"listed_count":17,"favourites_count":534,"statuses_count":66844,"created_at":"Sat Jan 16 02:34:19 +0000 2010","utc_offset":-14400,"time_zone":"Eastern Time (US & Canada)","geo_enabled":true,"lang":"en","contributors_enabled":false,"is_translator":false,"profile_background_color":"C0DEED","profile_background_image_url":"http:\/\/pbs.twimg.com\/profile_background_images\/360375352\/game_winner.jpg","profile_background_image_url_https":"https:\/\/pbs.twimg.com\/profile_background_images\/360375352\/game_winner.jpg","profile_background_tile":true,"profile_link_color":"0084B4","profile_sidebar_border_color":"C0DEED","profile_sidebar_fill_color":"DDEEF6","profile_text_color":"333333","profile_use_background_image":true,"profile_image_url":"http:\/\/pbs.twimg.com\/profile_images\/484693527658393600\/t6TCkEIK_normal.jpeg","profile_image_url_https":"https:\/\/pbs.twimg.com\/profile_images\/484693527658393600\/t6TCkEIK_normal.jpeg","profile_banner_url":"https:\/\/pbs.twimg.com\/profile_banners\/105344421\/1424058496","default_profile":false,"default_profile_image":false,"following":null,"follow_request_sent":null,"notifications":null},"geo":null,"coordinates":null,"place":null,"contributors":null,"retweet_count":0,"favorite_count":0,"entities":{"hashtags":[],"trends":[],"urls":[],"user_mentions":[],"symbols":[]},"favorited":false,"retweeted":false,"possibly_sensitive":false,"filter_level":"low","lang":"en","timestamp_ms":"1442087689236"}
