{"created_at":"Thu Sep 10 20:24:32 +0000 2015","id":642071179151347712,"id_str":"642071179151347712","text":"RT @nasseratta5: #Syria rejects #British proposal for #Assad to lead transitional government http:\/\/t.co\/qH5nKWYM7B","source":"\u003ca href=\"http:\/\/twitter.com\/download\/iphone\" rel=\"nofollow\"\u003eTwitter for iPhone\u003c\/a\u003e","truncated":false,"in_reply_to_status_id":null,"in_reply_to_status_id_str":null,"in_reply_to_user_id":null,"in_reply_to_user_id_str":null,"in_reply_to_screen_name":null,"user":{"id":438202941,"id_str":"438202941","name":"Beezibee","screen_name":"bzB10","location":" \u0627\u0644\u062e\u0631\u0648\u0641_\u0627\u0644\u0648\u062f\u064a\u0639 ","url":null,"description":"Look deep... If you see a sheep then you see yourself...","protected":false,"verified":false,"followers_count":71,"friends_count":162,"listed_count":0,"favourites_count":4968,"statuses_count":4469,"created_at":"Fri Dec 16 09:22:12 +0000 2011","utc_offset":null,"time_zone":null,"geo_enabled":false,"lang":"en","contributors_enabled":false,"is_translator":false,"profile_background_color":"C0DEED","profile_background_image_url":"http:\/\/abs.twimg.com\/images\/themes\/theme1\/bg.png","profile_background_image_url_https":"https:\/\/abs.twimg.com\/images\/themes\/theme1\/bg.png","profile_background_tile":false,"profile_link_color":"0084B4","profile_sidebar_border_color":"C0DEED","profile_sidebar_fill_color":"DDEEF6","profile_text_color":"333333","profile_use_background_image":true,"profile_image_url":"http:\/\/pbs.twimg.com\/profile_images\/378800000468336499\/53e08faccf16bf72083340db85617762_normal.jpeg","profile_image_url_https":"https:\/\/pbs.twimg.com\/profile_images\/378800000468336499\/53e08faccf16bf72083340db85617762_normal.jpeg","default_profile":true,"default_profile_image":false,"following":null,"follow_request_sent":null,"notifications":null},"geo":null,"coordinates":null,"place":null,"contributors":null,"retweeted_status":{"created_at":"Thu Sep 10 19:50:12 +0000 2015","id":642062537777893377,"id_str":"642062537777893377","text":"#Syria rejects #British proposal for #Assad to lead transitional government http:\/\/t.co\/qH5nKWYM7B","source":"\u003ca href=\"http:\/\/twitter.com\" rel=\"nofollow\"\u003eTwitter Web Client\u003c\/a\u003e","truncated":false,"in_reply_to_status_id":null,"in_reply_to_status_id_str":null,"in_reply_to_user_id":null,"in_reply_to_user_id_str":null,"in_reply_to_screen_name":null,"user":{"id":246471208,"id_str":"246471208","name":"Nasser Atta","screen_name":"nasseratta5","location":"MIddle East","url":"https:\/\/twitter.com\/settings\/profile","description":"Nasser Atta is ABC NEWS Producer in the Middle East,Tweeting my personal opinions, retweets is not an endorsement.","protected":false,"verified":false,"followers_count":5178,"friends_count":882,"listed_count":384,"favourites_count":619,"statuses_count":22301,"created_at":"Wed Feb 02 21:10:13 +0000 2011","utc_offset":-36000,"time_zone":"Hawaii","geo_enabled":true,"lang":"en","contributors_enabled":false,"is_translator":false,"profile_background_color":"C0DEED","profile_background_image_url":"http:\/\/abs.twimg.com\/images\/themes\/theme1\/bg.png","profile_background_image_url_https":"https:\/\/abs.twimg.com\/images\/themes\/theme1\/bg.png","profile_background_tile":false,"profile_link_color":"0084B4","profile_sidebar_border_color":"C0DEED","profile_sidebar_fill_color":"DDEEF6","profile_text_color":"333333","profile_use_background_image":true,"profile_image_url":"http:\/\/pbs.twimg.com\/profile_images\/592711470124814336\/9raNXKFr_normal.jpg","profile_image_url_https":"https:\/\/pbs.twimg.com\/profile_images\/592711470124814336\/9raNXKFr_normal.jpg","profile_banner_url":"https:\/\/pbs.twimg.com\/profile_banners\/246471208\/1426796973","default_profile":true,"default_profile_image":false,"following":null,"follow_request_sent":null,"notifications":null},"geo":null,"coordinates":null,"place":null,"contributors":null,"retweet_count":3,"favorite_count":0,"entities":{"hashtags":[{"text":"Syria","indices":[0,6]},{"text":"British","indices":[15,23]},{"text":"Assad","indices":[37,43]}],"trends":[],"urls":[{"url":"http:\/\/t.co\/qH5nKWYM7B","expanded_url":"http:\/\/gu.com\/p\/4c9zv\/stw","display_url":"gu.com\/p\/4c9zv\/stw","indices":[76,98]}],"user_mentions":[],"symbols":[]},"favorited":false,"retweeted":false,"possibly_sensitive":false,"filter_level":"low","lang":"en"},"retweet_count":0,"favorite_count":0,"entities":{"hashtags":[{"text":"Syria","indices":[17,23]},{"text":"British","indices":[32,40]},{"text":"Assad","indices":[54,60]}],"trends":[],"urls":[{"url":"http:\/\/t.co\/qH5nKWYM7B","expanded_url":"http:\/\/gu.com\/p\/4c9zv\/stw","display_url":"gu.com\/p\/4c9zv\/stw","indices":[93,115]}],"user_mentions":[{"screen_name":"nasseratta5","name":"Nasser Atta","id":246471208,"id_str":"246471208","indices":[3,15]}],"symbols":[]},"favorited":false,"retweeted":false,"possibly_sensitive":false,"filter_level":"low","lang":"en","timestamp_ms":"1441916672872"}
